odoo10_addon_mail_forward-10.0.1.0.0.99.dev4-py3.8-nspkg.pth
odoo/addons/mail_forward/README.rst
odoo/addons/mail_forward/__init__.py
odoo/addons/mail_forward/__manifest__.py
odoo/addons/mail_forward/i18n/es.po
odoo/addons/mail_forward/i18n/mail_forward.pot
odoo/addons/mail_forward/models/__init__.py
odoo/addons/mail_forward/models/compose_message.py
odoo/addons/mail_forward/models/res_request_link.py
odoo/addons/mail_forward/static/description/icon.png
odoo/addons/mail_forward/static/src/css/mail_forward.less
odoo/addons/mail_forward/static/src/js/mail_forward.js
odoo/addons/mail_forward/static/src/xml/mail_forward.xml
odoo/addons/mail_forward/tests/__init__.py
odoo/addons/mail_forward/tests/test_compose_message.py
odoo/addons/mail_forward/views/assets.xml
odoo/addons/mail_forward/views/compose_message.xml
odoo/addons/mail_forward/views/res_request_link.xml
odoo10_addon_mail_forward-10.0.1.0.0.99.dev4.dist-info/METADATA
odoo10_addon_mail_forward-10.0.1.0.0.99.dev4.dist-info/WHEEL
odoo10_addon_mail_forward-10.0.1.0.0.99.dev4.dist-info/namespace_packages.txt
odoo10_addon_mail_forward-10.0.1.0.0.99.dev4.dist-info/top_level.txt
odoo10_addon_mail_forward-10.0.1.0.0.99.dev4.dist-info/RECORD
